pandas_spectroscopy/__init__.py
pandas_spectroscopy-0.0.1.dist-info/METADATA
pandas_spectroscopy-0.0.1.dist-info/WHEEL
pandas_spectroscopy-0.0.1.dist-info/top_level.txt
pandas_spectroscopy-0.0.1.dist-info/RECORD
